lemonpy_mgng/__init__.py
lemonpy_mgng/helpers.py
lemonpy_mgng/mgng.py
lemonpy_mgng/validators.py
lemonpy_mgng-0.1.1.dist-info/WHEEL
lemonpy_mgng-0.1.1.dist-info/LICENSE
lemonpy_mgng-0.1.1.dist-info/METADATA
lemonpy_mgng-0.1.1.dist-info/RECORD
