Metadata-Version: 2.1
Name: lemonpy-mgng
Version: 0.1.1
Summary: mgng
License: MIT
Author: Stefan Ulbrich
Author-email: 6009224+stefanulbric@users.noreply.github.com
Requires-Python: >=3.7.2,<4.0
Classifier: License :: OSI Approved :: MIT License
Classifier: Programming Language :: Python :: 3
Classifier: Programming Language :: Python :: 3.8
Classifier: Programming Language :: Python :: 3.9
Classifier: Programming Language :: Python :: 3.10
Classifier: Programming Language :: Python :: 3.11
Classifier: Programming Language :: Python :: 3 :: Only
Classifier: Topic :: Scientific/Engineering :: Artificial Intelligence
Requires-Dist: attrs (>=22.1.0,<23.0.0)
Requires-Dist: numpy (>=1.18.1,<2.0.0)
